cantools/__init__.py
cantools/_db.py
cantools/_memcache.py
cantools/_pay.py
cantools/admin.py
cantools/cfg.py
cantools/config.py
cantools/geo.py
cantools/hooks.py
cantools/db/__init__.py
cantools/db/admin.py
cantools/db/wp.py
cantools/db/gae/__init__.py
cantools/db/gae/model.py
cantools/db/gae/properties.py
cantools/scripts/__init__.py
cantools/scripts/bench.py
cantools/scripts/builder.py
cantools/scripts/deploy.py
cantools/scripts/doc.py
cantools/scripts/index.py
cantools/scripts/init.py
cantools/scripts/migrate.py
cantools/scripts/start.py
cantools/scripts/util.py
cantools/scripts/pubsub/__init__.py
cantools/scripts/pubsub/actor.py
cantools/scripts/pubsub/bots.py
cantools/scripts/pubsub/channel.py
cantools/scripts/pubsub/ps.py
cantools/scripts/pubsub/user.py
cantools/util/__init__.py
cantools/util/admin.py
cantools/util/data.py
cantools/util/media.py
cantools/util/package.py
cantools/util/system.py
cantools/util/ai/__init__.py
cantools/util/ai/vox.py
cantools/util/ai/tox/__init__.py
cantools/util/ai/tox/duck.py
cantools/util/ai/tox/fzn.py
cantools/util/ai/tox/g4free.py
cantools/util/apper/__init__.py
cantools/util/apper/ander.py
cantools/util/apper/data.py
cantools/web/__init__.py
cantools/web/bw.py
cantools/web/gae_server.py
cantools/web/util.py
ct-0.10.8.116.dist-info/LICENSE
ct-0.10.8.116.dist-info/METADATA
ct-0.10.8.116.dist-info/WHEEL
ct-0.10.8.116.dist-info/entry_points.txt
ct-0.10.8.116.dist-info/top_level.txt
ct-0.10.8.116.dist-info/RECORD
