Metadata-Version: 2.1
Name: ct
Version: 0.10.8.116
Summary: Modern minimal web framework
Author: Mario Balibrera
Author-email: mario.balibrera@gmail.com
License: MIT License
Classifier: Development Status :: 5 - Production/Stable
Classifier: Environment :: Console
Classifier: Intended Audience :: Developers
Classifier: License :: OSI Approved :: MIT License
Classifier: Operating System :: OS Independent
Classifier: Programming Language :: Python
Classifier: Topic :: Software Development :: Libraries :: Python Modules
License-File: LICENSE
Requires-Dist: babyweb >=0.1.2
Requires-Dist: catmail >=0.1.9.1
Requires-Dist: databae >=0.1.5.1
Requires-Dist: dez >=0.10.10.45
Requires-Dist: fyg >=0.1.7.9
Requires-Dist: rel >=0.4.9.23
Requires-Dist: venvr >=0.1.5.8
